flit_sch_test/__init__.py
flit_sch_test-0.0.1.dist-info/LICENSE
flit_sch_test-0.0.1.dist-info/WHEEL
flit_sch_test-0.0.1.dist-info/METADATA
flit_sch_test-0.0.1.dist-info/RECORD
